./.gitignore
./PKG-INFO
./README.md
./main.py
./pyproject.toml
truffle_ai_domain_checker_mcp-1.0.2.dist-info/METADATA
truffle_ai_domain_checker_mcp-1.0.2.dist-info/WHEEL
truffle_ai_domain_checker_mcp-1.0.2.dist-info/entry_points.txt
truffle_ai_domain_checker_mcp-1.0.2.dist-info/RECORD
