Metadata-Version: 2.4
Name: truffle-ai-domain-checker-mcp
Version: 1.0.2
Summary: MCP server for checking domain name availability
Project-URL: Homepage, https://github.com/truffle-ai/mcp-servers
Project-URL: Repository, https://github.com/truffle-ai/mcp-servers
Project-URL: Issues, https://github.com/truffle-ai/mcp-servers/issues
Author-email: Truffle AI <founders@trytruffle.ai>
License: MIT
Keywords: domain,mcp,saiki,truffle-ai,whois
Classifier: Development Status :: 4 - Beta
Classifier: Intended Audience :: Developers
Classifier: License :: OSI Approved :: MIT License
Classifier: Programming Language :: Python :: 3
Classifier: Programming Language :: Python :: 3.10
Classifier: Programming Language :: Python :: 3.11
Classifier: Programming Language :: Python :: 3.12
Classifier: Topic :: Software Development :: Libraries :: Python Modules
Requires-Python: >=3.10
Requires-Dist: aiohttp>=3.8.0
Requires-Dist: dnspython>=2.4.0
Requires-Dist: fastmcp>=0.1.0
Requires-Dist: uvicorn>=0.23.0
